[
  {
    "name": "ALTIN/GR (TL)",
    "buy_price": "ALTIN/GR (TL)",
    "sell_price": "6.801,34₺",
    "change_rate": "2,78%",
    "fetched_at": "2026-01-21 06:47:02"
  },
  {
    "name": "GÜMÜŞ/ONS (TL)",
    "buy_price": "GÜMÜŞ/ONS (TL)",
    "sell_price": "4.088,26₺",
    "change_rate": "0,32%",
    "fetched_at": "2026-01-21 06:47:02"
  },
  {
    "name": "HAM PETROL",
    "buy_price": "HAM PETROL",
    "sell_price": "59,74$",
    "change_rate": "-0,99%",
    "fetched_at": "2026-01-21 06:47:02"
  },
  {
    "name": "PALADYUM",
    "buy_price": "PALADYUM",
    "sell_price": "1.888,00$",
    "change_rate": "-0,89%",
    "fetched_at": "2026-01-21 06:47:02"
  },
  {
    "name": "BAKIR",
    "buy_price": "BAKIR",
    "sell_price": "5,87$",
    "change_rate": "0,68%",
    "fetched_at": "2026-01-21 06:47:02"
  },
  {
    "name": "BENZİN",
    "buy_price": "BENZİN",
    "sell_price": "1,81$",
    "change_rate": "-0,75%",
    "fetched_at": "2026-01-21 06:47:02"
  },
  {
    "name": "BRENT PETROL",
    "buy_price": "BRENT PETROL",
    "sell_price": "64,14$",
    "change_rate": "-1,17%",
    "fetched_at": "2026-01-21 06:47:02"
  },
  {
    "name": "BUĞDAY",
    "buy_price": "BUĞDAY",
    "sell_price": "509,80$",
    "change_rate": "0,06%",
    "fetched_at": "2026-01-21 06:47:02"
  },
  {
    "name": "DOĞAL GAZ",
    "buy_price": "DOĞAL GAZ",
    "sell_price": "3,41$",
    "change_rate": "-12,36%",
    "fetched_at": "2026-01-21 06:47:02"
  },
  {
    "name": "KALORİFER YAKITI",
    "buy_price": "KALORİFER YAKITI",
    "sell_price": "2,35$",
    "change_rate": "1,36%",
    "fetched_at": "2026-01-21 06:47:02"
  },
  {
    "name": "MISIR",
    "buy_price": "MISIR",
    "sell_price": "423,90$",
    "change_rate": "0,09%",
    "fetched_at": "2026-01-21 06:47:02"
  },
  {
    "name": "PAMUK",
    "buy_price": "PAMUK",
    "sell_price": "64,27$",
    "change_rate": "0,11%",
    "fetched_at": "2026-01-21 06:47:02"
  },
  {
    "name": "PLATİN",
    "buy_price": "PLATİN",
    "sell_price": "2.437,20$",
    "change_rate": "-1,61%",
    "fetched_at": "2026-01-21 06:47:02"
  },
  {
    "name": "",
    "buy_price": "",
    "sell_price": "-",
    "change_rate": "0,00%",
    "fetched_at": "2026-01-21 06:47:02"
  },
  {
    "name": "SOYA FASULYESİ",
    "buy_price": "SOYA FASULYESİ",
    "sell_price": "1.058,00$",
    "change_rate": "0,56%",
    "fetched_at": "2026-01-21 06:47:02"
  },
  {
    "name": "KAKAO",
    "buy_price": "KAKAO",
    "sell_price": "4.653,00$",
    "change_rate": "-8,33%",
    "fetched_at": "2026-01-21 06:47:02"
  },
  {
    "name": "KAHVE",
    "buy_price": "KAHVE",
    "sell_price": "345,80$",
    "change_rate": "-2,67%",
    "fetched_at": "2026-01-21 06:47:02"
  },
  {
    "name": "ALTIN (GRAM)",
    "buy_price": "ALTIN (GRAM)",
    "sell_price": "6.801,50",
    "change_rate": "2,78%",
    "fetched_at": "2026-01-21 06:47:03"
  },
  {
    "name": "ALTIN (ONS)",
    "buy_price": "ALTIN (ONS)",
    "sell_price": "210.326,57",
    "change_rate": "2,21%",
    "fetched_at": "2026-01-21 06:47:03"
  },
  {
    "name": "Cumhuriyet Altını",
    "buy_price": "Cumhuriyet Altını",
    "sell_price": "44.291,00",
    "change_rate": "1,51%",
    "fetched_at": "2026-01-21 06:47:03"
  },
  {
    "name": "Çeyrek Altın",
    "buy_price": "Çeyrek Altın",
    "sell_price": "10.690,39",
    "change_rate": "0,00%",
    "fetched_at": "2026-01-21 06:47:03"
  },
  {
    "name": "Yarım Altın",
    "buy_price": "Yarım Altın",
    "sell_price": "21.313,96",
    "change_rate": "0,00%",
    "fetched_at": "2026-01-21 06:47:03"
  },
  {
    "name": "Ata Altın",
    "buy_price": "Ata Altın",
    "sell_price": "44.097,85",
    "change_rate": "0,00%",
    "fetched_at": "2026-01-21 06:47:03"
  },
  {
    "name": "TAM ALTIN",
    "buy_price": "TAM ALTIN",
    "sell_price": "44.024,00",
    "change_rate": "2,60%",
    "fetched_at": "2026-01-21 06:47:03"
  },
  {
    "name": "14 Ayar Bilezik Gramı",
    "buy_price": "14 Ayar Bilezik Gramı",
    "sell_price": "3.808,45",
    "change_rate": "0,00%",
    "fetched_at": "2026-01-21 06:47:03"
  },
  {
    "name": "22 Ayar Bilezik Gramı",
    "buy_price": "22 Ayar Bilezik Gramı",
    "sell_price": "6.093,52",
    "change_rate": "0,00%",
    "fetched_at": "2026-01-21 06:47:03"
  },
  {
    "name": "Altın Sertifikası",
    "buy_price": "Altın Sertifikası",
    "sell_price": "-",
    "change_rate": "0,00%",
    "fetched_at": "2026-01-21 06:47:03"
  },
  {
    "name": "22 Ayar Gram Altın",
    "buy_price": "22 Ayar Gram Altın",
    "sell_price": "6.093,52",
    "change_rate": "0,00%",
    "fetched_at": "2026-01-21 06:47:03"
  },
  {
    "name": "18 Ayar Gram Altın",
    "buy_price": "18 Ayar Gram Altın",
    "sell_price": "4.877,49",
    "change_rate": "0,00%",
    "fetched_at": "2026-01-21 06:47:03"
  },
  {
    "name": "14 Ayar Gram Altın",
    "buy_price": "14 Ayar Gram Altın",
    "sell_price": "3.808,45",
    "change_rate": "0,00%",
    "fetched_at": "2026-01-21 06:47:03"
  },
  {
    "name": "Gramse Altın",
    "buy_price": "Gramse Altın",
    "sell_price": "106.903,87",
    "change_rate": "0,00%",
    "fetched_at": "2026-01-21 06:47:03"
  },
  {
    "name": "Hamit Altın",
    "buy_price": "Hamit Altın",
    "sell_price": "42.761,55",
    "change_rate": "0,00%",
    "fetched_at": "2026-01-21 06:47:03"
  },
  {
    "name": "Has Altın",
    "buy_price": "Has Altın",
    "sell_price": "6.767,50",
    "change_rate": "2,78%",
    "fetched_at": "2026-01-21 06:47:03"
  },
  {
    "name": "Kapalı Çarşı Altın",
    "buy_price": "Kapalı Çarşı Altın",
    "sell_price": "6.801,50",
    "change_rate": "2,78%",
    "fetched_at": "2026-01-21 06:47:03"
  },
  {
    "name": "Ziynet Altın",
    "buy_price": "Ziynet Altın",
    "sell_price": "42.761,55",
    "change_rate": "0,00%",
    "fetched_at": "2026-01-21 06:47:03"
  },
  {
    "name": "Külçe Altın ($)",
    "buy_price": "Külçe Altın ($)",
    "sell_price": "153.500,00",
    "change_rate": "1,59%",
    "fetched_at": "2026-01-21 06:47:03"
  },
  {
    "name": "2.5'luk Altın",
    "buy_price": "2.5'luk Altın",
    "sell_price": "106.903,87",
    "change_rate": "0,00%",
    "fetched_at": "2026-01-21 06:47:03"
  },
  {
    "name": "Reşat Altın",
    "buy_price": "Reşat Altın",
    "sell_price": "42.761,55",
    "change_rate": "0,00%",
    "fetched_at": "2026-01-21 06:47:03"
  },
  {
    "name": "Beşli Altın",
    "buy_price": "Beşli Altın",
    "sell_price": "216.480,34",
    "change_rate": "0,00%",
    "fetched_at": "2026-01-21 06:47:03"
  }
]