[
  {
    "name": "ALTIN/GR (TL)",
    "buy_price": "ALTIN/GR (TL)",
    "sell_price": "7.027,17₺",
    "change_rate": "1,22%",
    "fetched_at": "2026-02-09 07:59:34"
  },
  {
    "name": "GÜMÜŞ/ONS (TL)",
    "buy_price": "GÜMÜŞ/ONS (TL)",
    "sell_price": "3.523,79₺",
    "change_rate": "4,37%",
    "fetched_at": "2026-02-09 07:59:34"
  },
  {
    "name": "HAM PETROL",
    "buy_price": "HAM PETROL",
    "sell_price": "62,71$",
    "change_rate": "-1,29%",
    "fetched_at": "2026-02-09 07:59:34"
  },
  {
    "name": "PALADYUM",
    "buy_price": "PALADYUM",
    "sell_price": "1.721,50$",
    "change_rate": "-0,86%",
    "fetched_at": "2026-02-09 07:59:34"
  },
  {
    "name": "BAKIR",
    "buy_price": "BAKIR",
    "sell_price": "5,89$",
    "change_rate": "0,18%",
    "fetched_at": "2026-02-09 07:59:34"
  },
  {
    "name": "BENZİN",
    "buy_price": "BENZİN",
    "sell_price": "1,94$",
    "change_rate": "-0,82%",
    "fetched_at": "2026-02-09 07:59:34"
  },
  {
    "name": "BRENT PETROL",
    "buy_price": "BRENT PETROL",
    "sell_price": "67,18$",
    "change_rate": "-1,25%",
    "fetched_at": "2026-02-09 07:59:34"
  },
  {
    "name": "BUĞDAY",
    "buy_price": "BUĞDAY",
    "sell_price": "527,60$",
    "change_rate": "-0,08%",
    "fetched_at": "2026-02-09 07:59:34"
  },
  {
    "name": "DOĞAL GAZ",
    "buy_price": "DOĞAL GAZ",
    "sell_price": "3,19$",
    "change_rate": "-6,58%",
    "fetched_at": "2026-02-09 07:59:34"
  },
  {
    "name": "KALORİFER YAKITI",
    "buy_price": "KALORİFER YAKITI",
    "sell_price": "2,37$",
    "change_rate": "-1,60%",
    "fetched_at": "2026-02-09 07:59:34"
  },
  {
    "name": "MISIR",
    "buy_price": "MISIR",
    "sell_price": "429,25$",
    "change_rate": "0,09%",
    "fetched_at": "2026-02-09 07:59:34"
  },
  {
    "name": "PAMUK",
    "buy_price": "PAMUK",
    "sell_price": "61,15$",
    "change_rate": "0,25%",
    "fetched_at": "2026-02-09 07:59:34"
  },
  {
    "name": "PLATİN",
    "buy_price": "PLATİN",
    "sell_price": "2.083,70$",
    "change_rate": "-0,59%",
    "fetched_at": "2026-02-09 07:59:34"
  },
  {
    "name": "ŞEKER",
    "buy_price": "ŞEKER",
    "sell_price": "14,13$",
    "change_rate": "-0,91%",
    "fetched_at": "2026-02-09 07:59:34"
  },
  {
    "name": "SOYA FASULYESİ",
    "buy_price": "SOYA FASULYESİ",
    "sell_price": "1.110,25$",
    "change_rate": "-0,41%",
    "fetched_at": "2026-02-09 07:59:34"
  },
  {
    "name": "KAKAO",
    "buy_price": "KAKAO",
    "sell_price": "4.150,00$",
    "change_rate": "-1,31%",
    "fetched_at": "2026-02-09 07:59:34"
  },
  {
    "name": "KAHVE",
    "buy_price": "KAHVE",
    "sell_price": "293,85$",
    "change_rate": "-3,84%",
    "fetched_at": "2026-02-09 07:59:34"
  },
  {
    "name": "ALTIN (GRAM)",
    "buy_price": "ALTIN (GRAM)",
    "sell_price": "7.027,12",
    "change_rate": "1,22%",
    "fetched_at": "2026-02-09 07:59:35"
  },
  {
    "name": "ALTIN (ONS)",
    "buy_price": "ALTIN (ONS)",
    "sell_price": "218.268,15",
    "change_rate": "1,09%",
    "fetched_at": "2026-02-09 07:59:35"
  },
  {
    "name": "Cumhuriyet Altını",
    "buy_price": "Cumhuriyet Altını",
    "sell_price": "49.597,00",
    "change_rate": "0,86%",
    "fetched_at": "2026-02-09 07:59:35"
  },
  {
    "name": "Çeyrek Altın",
    "buy_price": "Çeyrek Altın",
    "sell_price": "11.792,60",
    "change_rate": "0,00%",
    "fetched_at": "2026-02-09 07:59:35"
  },
  {
    "name": "Yarım Altın",
    "buy_price": "Yarım Altın",
    "sell_price": "23.511,49",
    "change_rate": "0,00%",
    "fetched_at": "2026-02-09 07:59:35"
  },
  {
    "name": "Ata Altın",
    "buy_price": "Ata Altın",
    "sell_price": "48.644,46",
    "change_rate": "0,00%",
    "fetched_at": "2026-02-09 07:59:35"
  },
  {
    "name": "TAM ALTIN",
    "buy_price": "TAM ALTIN",
    "sell_price": "47.734,00",
    "change_rate": "1,61%",
    "fetched_at": "2026-02-09 07:59:35"
  },
  {
    "name": "14 Ayar Bilezik Gramı",
    "buy_price": "14 Ayar Bilezik Gramı",
    "sell_price": "4.201,11",
    "change_rate": "0,00%",
    "fetched_at": "2026-02-09 07:59:35"
  },
  {
    "name": "22 Ayar Bilezik Gramı",
    "buy_price": "22 Ayar Bilezik Gramı",
    "sell_price": "6.721,78",
    "change_rate": "0,00%",
    "fetched_at": "2026-02-09 07:59:35"
  },
  {
    "name": "Altın Sertifikası",
    "buy_price": "Altın Sertifikası",
    "sell_price": "87,07",
    "change_rate": "0,93%",
    "fetched_at": "2026-02-09 07:59:35"
  },
  {
    "name": "22 Ayar Gram Altın",
    "buy_price": "22 Ayar Gram Altın",
    "sell_price": "6.721,78",
    "change_rate": "0,00%",
    "fetched_at": "2026-02-09 07:59:35"
  },
  {
    "name": "18 Ayar Gram Altın",
    "buy_price": "18 Ayar Gram Altın",
    "sell_price": "5.380,37",
    "change_rate": "0,00%",
    "fetched_at": "2026-02-09 07:59:35"
  },
  {
    "name": "14 Ayar Gram Altın",
    "buy_price": "14 Ayar Gram Altın",
    "sell_price": "4.201,11",
    "change_rate": "0,00%",
    "fetched_at": "2026-02-09 07:59:35"
  },
  {
    "name": "Gramse Altın",
    "buy_price": "Gramse Altın",
    "sell_price": "117.925,97",
    "change_rate": "0,00%",
    "fetched_at": "2026-02-09 07:59:35"
  },
  {
    "name": "Hamit Altın",
    "buy_price": "Hamit Altın",
    "sell_price": "47.170,39",
    "change_rate": "0,00%",
    "fetched_at": "2026-02-09 07:59:35"
  },
  {
    "name": "Has Altın",
    "buy_price": "Has Altın",
    "sell_price": "6.991,98",
    "change_rate": "1,22%",
    "fetched_at": "2026-02-09 07:59:35"
  },
  {
    "name": "Kapalı Çarşı Altın",
    "buy_price": "Kapalı Çarşı Altın",
    "sell_price": "7.027,12",
    "change_rate": "1,22%",
    "fetched_at": "2026-02-09 07:59:35"
  },
  {
    "name": "Ziynet Altın",
    "buy_price": "Ziynet Altın",
    "sell_price": "47.170,39",
    "change_rate": "0,00%",
    "fetched_at": "2026-02-09 07:59:35"
  },
  {
    "name": "Külçe Altın ($)",
    "buy_price": "Külçe Altın ($)",
    "sell_price": "167.700,00",
    "change_rate": "0,78%",
    "fetched_at": "2026-02-09 07:59:35"
  },
  {
    "name": "2.5'luk Altın",
    "buy_price": "2.5'luk Altın",
    "sell_price": "117.925,97",
    "change_rate": "0,00%",
    "fetched_at": "2026-02-09 07:59:35"
  },
  {
    "name": "Reşat Altın",
    "buy_price": "Reşat Altın",
    "sell_price": "47.170,39",
    "change_rate": "0,00%",
    "fetched_at": "2026-02-09 07:59:35"
  },
  {
    "name": "Beşli Altın",
    "buy_price": "Beşli Altın",
    "sell_price": "238.800,09",
    "change_rate": "0,00%",
    "fetched_at": "2026-02-09 07:59:35"
  }
]